{"cameraMode":{"drawMode":0,"name":"Shaded","section":"Shading Mode"},"sceneLighting":true,"audioPlay":false,"sceneViewState":{"m_AlwaysRefresh":false,"showFog":true,"showSkybox":true,"showFlares":true,"showImageEffects":true,"showParticleSystems":true,"showVisualEffectGraphs":true,"m_FxEnabled":true},"in2DMode":false,"pivot":{"x":139.193359375,"y":10.556181907653809,"z":213.1736602783203},"rotation":{"x":0.0014539427356794477,"y":0.990811824798584,"z":-0.13488991558551789,"w":0.010700954124331475},"size":9.055254936218262,"orthographic":false}